nomad_camels_driver_ni_daq/daq_signal.py
nomad_camels_driver_ni_daq/ni_daq.py
nomad_camels_driver_ni_daq/ni_daq_ophyd.py
nomad_camels_driver_ni_daq-0.1.1.dist-info/LICENSE.txt
nomad_camels_driver_ni_daq-0.1.1.dist-info/METADATA
nomad_camels_driver_ni_daq-0.1.1.dist-info/WHEEL
nomad_camels_driver_ni_daq-0.1.1.dist-info/top_level.txt
nomad_camels_driver_ni_daq-0.1.1.dist-info/RECORD
